CollectionFramework/__init__.py
CollectionFramework/__init_py
CollectionFramework/collection.py
unique_chars_counter_vs-0.1.0.dist-info/METADATA
unique_chars_counter_vs-0.1.0.dist-info/WHEEL
unique_chars_counter_vs-0.1.0.dist-info/licenses/LICENSE
unique_chars_counter_vs-0.1.0.dist-info/RECORD
