Metadata-Version: 2.4
Name: unique-chars-counter-vs
Version: 0.1.0
Summary: A command-line tool for counting unique characters in strings or files
Project-URL: Repository, https://git.foxminded.ua/foxstudent106775/task_4_cli.git
Author-email: Volodymyr Savchenko <your.email@example.com>
License-File: LICENSE
Classifier: License :: OSI Approved :: MIT License
Classifier: Programming Language :: Python :: 3
Classifier: Programming Language :: Python :: 3.10
Requires-Python: >=3.10
